integration/README.md
integration/__init__.py
integration/docker_manager_test.py
integration/gcluster_a3mega_test.py
integration/gcluster_a3ultra_test.py
integration/gcluster_a4_test.py
integration/gcluster_test.py
xpk/__init__.py
xpk/main.py
xpk/telemetry_uploader.py
xpk/api/__init__.py
xpk/api/storage_crd.yaml
xpk/blueprints/a3mega/config-map.yaml.tftpl
xpk/blueprints/a3mega/storage_crd.yaml
xpk/blueprints/a3ultra/config-map.yaml.tftpl
xpk/blueprints/a3ultra/mlgru-disable.yaml
xpk/blueprints/a3ultra/nccl-installer.yaml
xpk/blueprints/a3ultra/storage_crd.yaml
xpk/blueprints/a4/config-map.yaml.tftpl
xpk/blueprints/a4/nccl-rdma-installer-a4.yaml
xpk/blueprints/a4/storage_crd.yaml
xpk/commands/__init__.py
xpk/commands/cluster.py
xpk/commands/cluster_gcluster.py
xpk/commands/cluster_gcluster_test.py
xpk/commands/cluster_test.py
xpk/commands/common.py
xpk/commands/config.py
xpk/commands/info.py
xpk/commands/inspector.py
xpk/commands/kind.py
xpk/commands/managed_ml_diagnostics.py
xpk/commands/managed_ml_diagnostics_test.py
xpk/commands/storage.py
xpk/commands/version.py
xpk/commands/workload.py
xpk/commands/workload_test.py
xpk/core/__init__.py
xpk/core/capacity.py
xpk/core/capacity_test.py
xpk/core/cluster.py
xpk/core/cluster_private.py
xpk/core/cluster_test.py
xpk/core/commands.py
xpk/core/config.py
xpk/core/config_test.py
xpk/core/docker_container.py
xpk/core/docker_image.py
xpk/core/docker_manager.py
xpk/core/docker_resources.py
xpk/core/filestore.py
xpk/core/gcloud_context.py
xpk/core/gcloud_context_test.py
xpk/core/gcluster_manager.py
xpk/core/gcsfuse.py
xpk/core/jobset.py
xpk/core/kueue_manager.py
xpk/core/kueue_manager_test.py
xpk/core/monitoring.py
xpk/core/mtc.py
xpk/core/nap.py
xpk/core/network.py
xpk/core/nodepool.py
xpk/core/nodepool_test.py
xpk/core/pathways.py
xpk/core/pathways_test.py
xpk/core/ray.py
xpk/core/resources.py
xpk/core/scheduling.py
xpk/core/scheduling_test.py
xpk/core/storage.py
xpk/core/system_characteristics.py
xpk-0.17.3.dist-info/licenses/LICENSE
xpk-0.17.3.dist-info/METADATA
xpk-0.17.3.dist-info/WHEEL
xpk-0.17.3.dist-info/entry_points.txt
xpk-0.17.3.dist-info/top_level.txt
xpk-0.17.3.dist-info/RECORD
