Metadata-Version: 2.4
Name: xpk
Version: 0.17.3
Summary: xpk helps Cloud developers to orchestrate training jobs on accelerators on GKE.
Author-email: XPK team <xpk-code-reviewers@google.com>
License: Apache-2.0
Project-URL: Homepage, https://github.com/google/xpk
Project-URL: Bug Tracker, https://github.com/google/xpk/issues
Classifier: Programming Language :: Python :: 3.10
Classifier: Programming Language :: Python :: 3.11
Requires-Python: >=3.10
License-File: LICENSE
Requires-Dist: argcomplete==3.6.3
Requires-Dist: cloud-accelerator-diagnostics==0.1.1
Requires-Dist: tabulate==0.9.0
Requires-Dist: ruamel.yaml==0.18.10
Requires-Dist: setuptools-scm>=8
Requires-Dist: pyyaml==6.0.2
Requires-Dist: docker==7.1.0
Requires-Dist: kubernetes==31.0.0
Requires-Dist: google-cloud==0.34.0
Requires-Dist: google-api-core==2.24.1
Requires-Dist: packaging==24.2
Requires-Dist: google-cloud-filestore==1.12.0
Requires-Dist: google-cloud-storage
Requires-Dist: Jinja2==3.1.6
Requires-Dist: urllib3<2.6.0
Provides-Extra: dev
Requires-Dist: pyink==24.3.0; extra == "dev"
Requires-Dist: pylint>=2.6.0; extra == "dev"
Requires-Dist: pre-commit; extra == "dev"
Requires-Dist: pytest; extra == "dev"
Requires-Dist: pytest-mock==3.15.1; extra == "dev"
Requires-Dist: docker==7.1.0; extra == "dev"
Requires-Dist: mypy~=1.17; extra == "dev"
Requires-Dist: types-PyYAML==6.0.2; extra == "dev"
Requires-Dist: types-docker~=7.1.0.0; extra == "dev"
Requires-Dist: pylint-per-file-ignores==1.4.0; extra == "dev"
Dynamic: license-file
